[
    {
        "seal": "//upload.wikimedia.org/wikipedia/commons/thumb/8/82/Aceh_COA.svg/30px-Aceh_COA.svg.png",
        "province": "Special Region of Aceh",
        "iso_3": "ID-AC",
        "capital": "Banda Aceh",
        "population": "4,494,410",
        "area": "57,956",
        "population_density": "77",
        "geographical": "Sumatra",
        "number_of_cities": "5",
        "number_of_regencies": "18",
        "number_of_districts": "275",
        "number_of_villages": "6,420"
    },
    {
        "seal": "//upload.wikimedia.org/wikipedia/commons/thumb/2/21/Bali_COA.svg/30px-Bali_COA.svg.png",
        "province": "Bali",
        "iso_3": "ID-BA",
        "capital": "Denpasar",
        "population": "3,890,757",
        "area": "5,780",
        "population_density": "621",
        "geographical": "Lesser Sunda Islands",
        "number_of_cities": "1",
        "number_of_regencies": "8",
        "number_of_districts": "57",
        "number_of_villages": "698"
    },
    {
        "seal": "//upload.wikimedia.org/wikipedia/commons/thumb/5/5e/Bangka_Belitung_Emblem.svg/30px-Bangka_Belitung_Emblem.svg.png",
        "province": "Bangka–Belitung Islands",
        "iso_3": "ID-BB",
        "capital": "Pangkal Pinang",
        "population": "1,223,296",
        "area": "16,424",
        "population_density": "64",
        "geographical": "Sumatra",
        "number_of_cities": "1",
        "number_of_regencies": "6",
        "number_of_districts": "43",
        "number_of_villages": "361"
    },
    {
        "seal": "//upload.wikimedia.org/wikipedia/commons/thumb/1/1a/Banten_coa.png/30px-Banten_coa.png",
        "province": "Banten",
        "iso_3": "ID-BT",
        "capital": "Serang",
        "population": "10,632,166",
        "area": "9,662",
        "population_density": "909",
        "geographical": "Java",
        "number_of_cities": "4",
        "number_of_regencies": "4",
        "number_of_districts": "154",
        "number_of_villages": "1,530"
    },
    {
        "seal": "//upload.wikimedia.org/wikipedia/commons/thumb/0/03/Bengkulu_coa.png/30px-Bengkulu_coa.png",
        "province": "Bengkulu",
        "iso_3": "ID-BE",
        "capital": "Bengkulu",
        "population": "1,715,518",
        "area": "19,919",
        "population_density": "84",
        "geographical": "Sumatra",
        "number_of_cities": "1",
        "number_of_regencies": "9",
        "number_of_districts": "116",
        "number_of_villages": "1,442"
    },
    {
        "seal": "//upload.wikimedia.org/wikipedia/commons/thumb/4/4e/Central_Java_COA.svg/30px-Central_Java_COA.svg.png",
        "province": "Central Java",
        "iso_3": "ID-JT",
        "capital": "Semarang",
        "population": "32,382,657",
        "area": "40,800",
        "population_density": "894",
        "geographical": "Java",
        "number_of_cities": "6",
        "number_of_regencies": "29",
        "number_of_districts": "573",
        "number_of_villages": "8,577"
    },
    {
        "seal": "//upload.wikimedia.org/wikipedia/commons/thumb/c/c3/Central_Kalimantan_coa.png/30px-Central_Kalimantan_coa.png",
        "province": "Central Kalimantan",
        "iso_3": "ID-KT",
        "capital": "Palangkaraya",
        "population": "2,212,089",
        "area": "153,564",
        "population_density": "14",
        "geographical": "Kalimantan",
        "number_of_cities": "1",
        "number_of_regencies": "13",
        "number_of_districts": "120",
        "number_of_villages": "1,439"
    },
    {
        "seal": "//upload.wikimedia.org/wikipedia/commons/thumb/e/e1/Central_Sulawesi_coa.png/30px-Central_Sulawesi_coa.png",
        "province": "Central Sulawesi",
        "iso_3": "ID-ST",
        "capital": "Palu",
        "population": "2,635,009",
        "area": "61,841",
        "population_density": "41",
        "geographical": "Sulawesi",
        "number_of_cities": "1",
        "number_of_regencies": "10",
        "number_of_districts": "147",
        "number_of_villages": "1,712"
    },
    {
        "seal": "//upload.wikimedia.org/wikipedia/commons/thumb/7/74/Coat_of_arms_of_East_Java.svg/30px-Coat_of_arms_of_East_Java.svg.png",
        "province": "East Java",
        "iso_3": "ID-JI",
        "capital": "Surabaya",
        "population": "37,476,757",
        "area": "47,799",
        "population_density": "828",
        "geographical": "Java",
        "number_of_cities": "9",
        "number_of_regencies": "29",
        "number_of_districts": "662",
        "number_of_villages": "8,502"
    },
    {
        "seal": "//upload.wikimedia.org/wikipedia/commons/thumb/4/47/East_kalimantan_coa.png/30px-East_kalimantan_coa.png",
        "province": "East Kalimantan[4]",
        "iso_3": "ID-KI",
        "capital": "Samarinda",
        "population": "3,026,060",
        "area": "139,462",
        "population_density": "22",
        "geographical": "Kalimantan",
        "number_of_cities": "3",
        "number_of_regencies": "6",
        "number_of_districts": "89",
        "number_of_villages": "1,023"
    },
    {
        "seal": "//upload.wikimedia.org/wikipedia/commons/thumb/7/7f/East_Nusa_Tenggara_COA.svg/30px-East_Nusa_Tenggara_COA.svg.png",
        "province": "East Nusa Tenggara",
        "iso_3": "ID-NT",
        "capital": "Kupang",
        "population": "4,683,827",
        "area": "48,718",
        "population_density": "92",
        "geographical": "Lesser Sunda Islands",
        "number_of_cities": "1",
        "number_of_regencies": "20",
        "number_of_districts": "286",
        "number_of_villages": "2,775"
    },
    {
        "seal": "//upload.wikimedia.org/wikipedia/commons/thumb/3/35/Lambang_propinsi_gorontalo.jpg/30px-Lambang_propinsi_gorontalo.jpg",
        "province": "Gorontalo",
        "iso_3": "ID-GO",
        "capital": "Gorontalo",
        "population": "1,040,164",
        "area": "11,257",
        "population_density": "94",
        "geographical": "Sulawesi",
        "number_of_cities": "1",
        "number_of_regencies": "5",
        "number_of_districts": "65",
        "number_of_villages": "595"
    },
    {
        "seal": "//upload.wikimedia.org/wikipedia/commons/thumb/9/90/Jakarta_COA.svg/30px-Jakarta_COA.svg.png",
        "province": "Jakarta (Special City District)",
        "iso_3": "ID-JK",
        "capital": "Jakarta",
        "population": "9,607,787",
        "area": "664",
        "population_density": "12,786",
        "geographical": "Java",
        "number_of_cities": "5",
        "number_of_regencies": "1",
        "number_of_districts": "44",
        "number_of_villages": "267"
    },
    {
        "seal": "//upload.wikimedia.org/wikipedia/commons/thumb/5/5b/Jambi_symbol.jpg/30px-Jambi_symbol.jpg",
        "province": "Jambi",
        "iso_3": "ID-JA",
        "capital": "Jambi",
        "population": "3,092,265",
        "area": "50,058",
        "population_density": "57",
        "geographical": "Sumatra",
        "number_of_cities": "2",
        "number_of_regencies": "9",
        "number_of_districts": "128",
        "number_of_villages": "1,319"
    },
    {
        "seal": "//upload.wikimedia.org/wikipedia/commons/thumb/b/b9/Lampung_coa.png/30px-Lampung_coa.png",
        "province": "Lampung",
        "iso_3": "ID-LA",
        "capital": "Bandar Lampung",
        "population": "7,608,405",
        "area": "34,623",
        "population_density": "226",
        "geographical": "Sumatra",
        "number_of_cities": "2",
        "number_of_regencies": "12",
        "number_of_districts": "206",
        "number_of_villages": "2,358"
    },
    {
        "seal": "//upload.wikimedia.org/wikipedia/commons/thumb/9/94/Maluku_coa.png/30px-Maluku_coa.png",
        "province": "Maluku",
        "iso_3": "ID-MA",
        "capital": "Ambon",
        "population": "1,533,506",
        "area": "46,914",
        "population_density": "32",
        "geographical": "Maluku Islands",
        "number_of_cities": "2",
        "number_of_regencies": "9",
        "number_of_districts": "76",
        "number_of_villages": "898"
    },
    {
        "seal": "//upload.wikimedia.org/wikipedia/commons/thumb/3/33/Emblem_of_North_Kalimantan.png/30px-Emblem_of_North_Kalimantan.png",
        "province": "North Kalimantan",
        "iso_3": "ID-KU",
        "capital": "Tanjung Selor",
        "population": "622,350",
        "area": "71,176",
        "population_density": "10",
        "geographical": "Kalimantan",
        "number_of_cities": "1",
        "number_of_regencies": "4",
        "number_of_districts": "47",
        "number_of_villages": "381"
    },
    {
        "seal": "//upload.wikimedia.org/wikipedia/commons/thumb/8/8f/North_Maluku_coa.png/30px-North_Maluku_coa.png",
        "province": "North Maluku",
        "iso_3": "ID-MU",
        "capital": "Sofifi",
        "population": "1,038,087",
        "area": "31,982",
        "population_density": "31",
        "geographical": "Maluku Islands",
        "number_of_cities": "2",
        "number_of_regencies": "7",
        "number_of_districts": "109",
        "number_of_villages": "1,041"
    },
    {
        "seal": "//upload.wikimedia.org/wikipedia/commons/thumb/d/dd/North_Sulawesi_Emblem.svg/30px-North_Sulawesi_Emblem.svg.png",
        "province": "North Sulawesi",
        "iso_3": "ID-SA",
        "capital": "Manado",
        "population": "2,270,596",
        "area": "13,851",
        "population_density": "162",
        "geographical": "Sulawesi",
        "number_of_cities": "4",
        "number_of_regencies": "11",
        "number_of_districts": "150",
        "number_of_villages": "1,510"
    },
    {
        "seal": "//upload.wikimedia.org/wikipedia/commons/thumb/b/b3/North_Sumatra_coa.png/30px-North_Sumatra_coa.png",
        "province": "North Sumatra",
        "iso_3": "ID-SU",
        "capital": "Medan",
        "population": "12,982,204",
        "area": "72,981",
        "population_density": "188",
        "geographical": "Sumatra",
        "number_of_cities": "8",
        "number_of_regencies": "25",
        "number_of_districts": "408",
        "number_of_villages": "5,649"
    },
    {
        "seal": "//upload.wikimedia.org/wikipedia/commons/thumb/3/36/Papua_COA.svg/30px-Papua_COA.svg.png",
        "province": "Special Region of Papua",
        "iso_3": "ID-PA",
        "capital": "Jayapura",
        "population": "2,833,381",
        "area": "319,036",
        "population_density": "8",
        "geographical": "Western New Guinea",
        "number_of_cities": "1",
        "number_of_regencies": "28",
        "number_of_districts": "330",
        "number_of_villages": "3,583"
    },
    {
        "seal": "//upload.wikimedia.org/wikipedia/commons/thumb/1/15/Riau_COA.svg/30px-Riau_COA.svg.png",
        "province": "Riau",
        "iso_3": "ID-RI",
        "capital": "Pekanbaru",
        "population": "5,538,367",
        "area": "87,023",
        "population_density": "52",
        "geographical": "Sumatra",
        "number_of_cities": "2",
        "number_of_regencies": "10",
        "number_of_districts": "153",
        "number_of_villages": "1,500"
    },
    {
        "seal": "//upload.wikimedia.org/wikipedia/commons/thumb/7/7f/Lambang_Riau_Kepulauan.jpeg/30px-Lambang_Riau_Kepulauan.jpeg",
        "province": "Riau Islands Province",
        "iso_3": "ID-KR",
        "capital": "Tanjung Pinang",
        "population": "1,679,163",
        "area": "8,201",
        "population_density": "208",
        "geographical": "Sumatra",
        "number_of_cities": "2",
        "number_of_regencies": "5",
        "number_of_districts": "59",
        "number_of_villages": "331"
    },
    {
        "seal": "//upload.wikimedia.org/wikipedia/commons/thumb/7/7f/Southeast_Sulawesi_COA.svg/30px-Southeast_Sulawesi_COA.svg.png",
        "province": "Southeast Sulawesi",
        "iso_3": "ID-SG",
        "capital": "Kendari",
        "population": "2,232,586",
        "area": "38,067",
        "population_density": "51",
        "geographical": "Sulawesi",
        "number_of_cities": "2",
        "number_of_regencies": "10",
        "number_of_districts": "199",
        "number_of_villages": "1,843"
    },
    {
        "seal": "//upload.wikimedia.org/wikipedia/commons/thumb/2/2b/South_Kalimantan_coa.jpg/30px-South_Kalimantan_coa.jpg",
        "province": "South Kalimantan",
        "iso_3": "ID-KS",
        "capital": "Banjarmasin",
        "population": "3,626,616",
        "area": "38,744",
        "population_density": "96",
        "geographical": "Kalimantan",
        "number_of_cities": "2",
        "number_of_regencies": "11",
        "number_of_districts": "151",
        "number_of_villages": "1,973"
    },
    {
        "seal": "//upload.wikimedia.org/wikipedia/commons/thumb/c/c2/South_Sulawesi_coa.png/30px-South_Sulawesi_coa.png",
        "province": "South Sulawesi",
        "iso_3": "ID-SN",
        "capital": "Makassar",
        "population": "8,034,776",
        "area": "46,717",
        "population_density": "151",
        "geographical": "Sulawesi",
        "number_of_cities": "3",
        "number_of_regencies": "26",
        "number_of_districts": "301",
        "number_of_villages": "2,874"
    },
    {
        "seal": "//upload.wikimedia.org/wikipedia/commons/thumb/6/6d/South_Sumatra_COA.svg/30px-South_Sumatra_COA.svg.png",
        "province": "South Sumatra",
        "iso_3": "ID-SS",
        "capital": "Palembang",
        "population": "7,450,394",
        "area": "91,592",
        "population_density": "86",
        "geographical": "Sumatra",
        "number_of_cities": "4",
        "number_of_regencies": "11",
        "number_of_districts": "217",
        "number_of_villages": "2,869"
    },
    {
        "seal": "//upload.wikimedia.org/wikipedia/commons/thumb/0/07/West_Java_coa.png/30px-West_Java_coa.png",
        "province": "West Java",
        "iso_3": "ID-JB",
        "capital": "Bandung",
        "population": "43,053,732",
        "area": "35,377",
        "population_density": "1176",
        "geographical": "Java",
        "number_of_cities": "9",
        "number_of_regencies": "17",
        "number_of_districts": "625",
        "number_of_villages": "5,827"
    },
    {
        "seal": "//upload.wikimedia.org/wikipedia/commons/thumb/4/49/West_Kalimantan_Emblem.svg/30px-West_Kalimantan_Emblem.svg.png",
        "province": "West Kalimantan",
        "iso_3": "ID-KB",
        "capital": "Pontianak",
        "population": "4,395,983",
        "area": "147,307",
        "population_density": "30",
        "geographical": "Kalimantan",
        "number_of_cities": "2",
        "number_of_regencies": "12",
        "number_of_districts": "175",
        "number_of_villages": "1,777"
    },
    {
        "seal": "//upload.wikimedia.org/wikipedia/commons/thumb/8/8f/West_Nusa_Tenggara_coa.png/30px-West_Nusa_Tenggara_coa.png",
        "province": "West Nusa Tenggara",
        "iso_3": "ID-NB",
        "capital": "Mataram",
        "population": "4,500,212",
        "area": "18,572",
        "population_density": "234",
        "geographical": "Lesser Sunda Islands",
        "number_of_cities": "2",
        "number_of_regencies": "8",
        "number_of_districts": "116",
        "number_of_villages": "913"
    },
    {
        "seal": "//upload.wikimedia.org/wikipedia/commons/thumb/c/c2/West_Papua_Province_Emblem.svg/30px-West_Papua_Province_Emblem.svg.png",
        "province": "Special Region of West Papua",
        "iso_3": "ID-PB[5]",
        "capital": "Manokwari",
        "population": "760,422",
        "area": "97,024",
        "population_density": "8",
        "geographical": "Western New Guinea",
        "number_of_cities": "1",
        "number_of_regencies": "10",
        "number_of_districts": "149",
        "number_of_villages": "1,291"
    },
    {
        "seal": "//upload.wikimedia.org/wikipedia/commons/thumb/d/da/West_Sulawesi_coa.png/30px-West_Sulawesi_coa.png",
        "province": "West Sulawesi",
        "iso_3": "ID-SR",
        "capital": "Mamuju",
        "population": "1,158,651",
        "area": "16,787",
        "population_density": "73",
        "geographical": "Sulawesi",
        "number_of_cities": "0",
        "number_of_regencies": "5",
        "number_of_districts": "66",
        "number_of_villages": "564"
    },
    {
        "seal": "//upload.wikimedia.org/wikipedia/commons/thumb/f/f4/West_Sumatra_coa.svg/30px-West_Sumatra_coa.svg.png",
        "province": "West Sumatra",
        "iso_3": "ID-SB",
        "capital": "Padang",
        "population": "5,133,989",
        "area": "42,012",
        "population_density": "110",
        "geographical": "Sumatra",
        "number_of_cities": "7",
        "number_of_regencies": "12",
        "number_of_districts": "169",
        "number_of_villages": "964"
    },
    {
        "seal": "//upload.wikimedia.org/wikipedia/commons/thumb/9/9a/Yogyakarta_COA.svg/30px-Yogyakarta_COA.svg.png",
        "province": "Special Region of Yogyakarta",
        "iso_3": "ID-YO",
        "capital": "Yogyakarta",
        "population": "3,457,491",
        "area": "3,133",
        "population_density": "1,138",
        "geographical": "Java",
        "number_of_cities": "1",
        "number_of_regencies": "4",
        "number_of_districts": "78",
        "number_of_villages": "438"
    }
]